FAImageGen/__init__.py
FAImageGen/api_client.py
FAImageGen/fuzer.py
FAImageGen/harmonizer.py
FAImageGen/image_generation.py
InstantLight/__init__.py
InstantLight/api_client.py
InstantLight/image_generation.py
FAIsdk-1.3.3.dist-info/LICENSE
FAIsdk-1.3.3.dist-info/METADATA
FAIsdk-1.3.3.dist-info/WHEEL
FAIsdk-1.3.3.dist-info/top_level.txt
FAIsdk-1.3.3.dist-info/RECORD
