Metadata-Version: 2.1
Name: FAIsdk
Version: 1.3.3
Summary: Python SDK combining FAI  API modules
Home-page: https://github.com/FotographerAI/FAI_sdks/
Author: Saliou Kane
Author-email: saliou@fotographer.ai
Classifier: Programming Language :: Python :: 3
Classifier: License :: OSI Approved :: MIT License
Classifier: Operating System :: OS Independent
Requires-Python: >=3.6
License-File: LICENSE
Requires-Dist: requests
Requires-Dist: Pillow
